forms_builder/__init__.py
forms_builder/forms/__init__.py
forms_builder/forms/admin.py
forms_builder/forms/fields.py
forms_builder/forms/forms.py
forms_builder/forms/models.py
forms_builder/forms/settings.py
forms_builder/forms/signals.py
forms_builder/forms/tests.py
forms_builder/forms/urls.py
forms_builder/forms/utils.py
forms_builder/forms/views.py
forms_builder/forms/locale/cs/LC_MESSAGES/django.mo
forms_builder/forms/locale/cs/LC_MESSAGES/django.po
forms_builder/forms/locale/de/LC_MESSAGES/django.mo
forms_builder/forms/locale/de/LC_MESSAGES/django.po
forms_builder/forms/locale/es/LC_MESSAGES/django.mo
forms_builder/forms/locale/es/LC_MESSAGES/django.po
forms_builder/forms/locale/fr/LC_MESSAGES/django.mo
forms_builder/forms/locale/fr/LC_MESSAGES/django.po
forms_builder/forms/locale/nb/LC_MESSAGES/django.mo
forms_builder/forms/locale/nb/LC_MESSAGES/django.po
forms_builder/forms/locale/nl/LC_MESSAGES/django.mo
forms_builder/forms/locale/nl/LC_MESSAGES/django.po
forms_builder/forms/locale/pl/LC_MESSAGES/django.mo
forms_builder/forms/locale/pl/LC_MESSAGES/django.po
forms_builder/forms/locale/pt_BR/LC_MESSAGES/django.mo
forms_builder/forms/locale/pt_BR/LC_MESSAGES/django.po
forms_builder/forms/locale/ru/LC_MESSAGES/django.mo
forms_builder/forms/locale/ru/LC_MESSAGES/django.po
forms_builder/forms/locale/zh/LC_MESSAGES/django.mo
forms_builder/forms/locale/zh/LC_MESSAGES/django.po
forms_builder/forms/migrations/0001_initial.py
forms_builder/forms/migrations/0002_auto_20160418_0120.py
forms_builder/forms/migrations/0003_auto_20180522_0820.py
forms_builder/forms/migrations/0004_alter_form_sites.py
forms_builder/forms/migrations/__init__.py
forms_builder/forms/templates/admin/forms/change_form.html
forms_builder/forms/templates/admin/forms/change_list.html
forms_builder/forms/templates/admin/forms/entries.html
forms_builder/forms/templates/email_extras/base.html
forms_builder/forms/templates/email_extras/base.txt
django_forms_builder_cod-1.0.1.dist-info/AUTHORS
django_forms_builder_cod-1.0.1.dist-info/LICENSE
django_forms_builder_cod-1.0.1.dist-info/METADATA
django_forms_builder_cod-1.0.1.dist-info/WHEEL
django_forms_builder_cod-1.0.1.dist-info/top_level.txt
django_forms_builder_cod-1.0.1.dist-info/RECORD
