Metadata-Version: 2.2
Name: django-forms-builder-cod
Version: 1.0.1
Summary: A Django reusable app providing the ability for admin users to create their own forms and report
Home-page: https://github.com/CZ-NIC/django-forms-builder
Author: Stephen McDonald
Author-email: stephen.mc@gmail.com
Maintainer: Zdeněk Böhm, CZ.NIC
Maintainer-email: zdenek.bohm@nic.cz
License: BSD
Platform: posix
Classifier: Development Status :: 5 - Production/Stable
Classifier: Environment :: Web Environment
Classifier: Intended Audience :: Developers
Classifier: Operating System :: OS Independent
Classifier: Programming Language :: Python
Classifier: Programming Language :: Python :: 3
Classifier: Programming Language :: Python :: 3.9
Classifier: Programming Language :: Python :: 3.10
Classifier: Framework :: Django
Classifier: Topic :: Internet :: WWW/HTTP :: Dynamic Content
Classifier: Topic :: Internet :: WWW/HTTP :: Site Management
Requires-Python: >=3.9
License-File: LICENSE
License-File: AUTHORS
Requires-Dist: django<6.0.0,>=3.2
Requires-Dist: unidecode~=1.3
Provides-Extra: quality
Requires-Dist: flake8; extra == "quality"
Requires-Dist: isort; extra == "quality"
Requires-Dist: mypy; extra == "quality"
Requires-Dist: polint; extra == "quality"
Requires-Dist: pydocstyle; extra == "quality"
